<?xml version="1.0" encoding="UTF-8" ?>

<forms>
	<form name="TAXVECINFOQUERY" title="出租车查询" pojo="TAXVECINFO" method="get" action="/cms/sitemanage/applicationIndex.shtml?applicationName=traffic/road&amp;pageName=TAXVECINFOQUERY">
		<!-- formFields>
			<field name="T2.BRACOLOR" title="车牌颜色编码" inputMode="hidden"/>
			<field name="T2.BRACOLOR_TITLE" title="车牌颜色" inputMode="dropdown">
				<parameter name="itemsServiceName">trafficSqlQueryService</parameter>
				<parameter name="itemsSql">select name, code from t_pf_datadict where ddfld='VECCOLOR' order by code</parameter>
				<parameter name="valueField">T2.BRACOLOR</parameter>
			</field>
		</formFields -->
		<actions>
			<action title="搜索" type="submit"/>
		</actions>
	</form>
		
	<form name="ENPSNDRIVERQUERY" title="出租车驾驶员查询" pojo="ENPSNDRIVER" method="get" action="/cms/sitemanage/applicationIndex.shtml?applicationName=traffic/road&amp;pageName=ENPSNDRIVERQUERY">
		<actions>
			<action title="搜索" type="submit"/>
		</actions>
	</form>
	
	<form name="TAXCLTQUERY" title="出租车业户查询" pojo="TAXCLT" method="get" action="/cms/sitemanage/applicationIndex.shtml?applicationName=traffic/road&amp;pageName=TAXCLTQUERY">
		<actions>
			<action title="搜索" type="submit"/>
		</actions>
	</form>
	
	<form name="ENCLTPASSTAQUERY" title="客运场站查询" pojo="ENCLTPASSTA" method="get" action="/cms/sitemanage/applicationIndex.shtml?applicationName=traffic/road&amp;pageName=ENCLTPASSTAQUERY">
		<actions>
			<action title="搜索" type="submit"/>
		</actions>
	</form>
	
	<form name="ENCLTDRVSCHQUERY" title="驾校查询" pojo="ENCLTDRVSCH" method="get" action="/cms/sitemanage/applicationIndex.shtml?applicationName=traffic/road&amp;pageName=ENCLTDRVSCHQUERY">
		<actions>
			<action title="搜索" type="submit"/>
		</actions>
	</form>
	
	<form name="ENVECCOACHQUERY" title="教练车查询" pojo="ENVECCOACH" method="get" action="/cms/sitemanage/applicationIndex.shtml?applicationName=traffic/road&amp;pageName=ENVECCOACHQUERY">
		<actions>
			<action title="搜索" type="submit"/>
		</actions>
	</form>
	
	<form name="ENPSNCOACHQUERY" title="教练员查询" pojo="ENPSNCOACH" method="get" action="/cms/sitemanage/applicationIndex.shtml?applicationName=traffic/road&amp;pageName=ENPSNCOACHQUERY">
		<actions>
			<action title="搜索" type="submit"/>
		</actions>
	</form>
	
	<form name="ENCLTMTNQUERY" title="维修业户查询" pojo="ENCLTMTN" method="get" action="/cms/sitemanage/applicationIndex.shtml?applicationName=traffic/road&amp;pageName=ENCLTMTNQUERY">
		<actions>
			<action title="搜索" type="submit"/>
		</actions>
	</form>
	
	<form name="ENCLTPASQUERY" title="客运业户查询" pojo="ENCLTPAS" method="get" action="/cms/sitemanage/applicationIndex.shtml?applicationName=traffic/road&amp;pageName=ENCLTPASQUERY">
		<actions>
			<action title="搜索" type="submit"/>
		</actions>
	</form>
	
	<form name="ENTVECPASSERQUERY" title="客运车辆查询" pojo="ENTVECPASSER" method="get" action="/cms/sitemanage/applicationIndex.shtml?applicationName=traffic/road&amp;pageName=ENTVECPASSERQUERY">
		<actions>
			<action title="搜索" type="submit"/>
		</actions>
	</form>
	
	<form name="ENCLTFREQUERY" title="普货经营性运输企业查询" pojo="ENCLTFRE" method="get" action="/cms/sitemanage/applicationIndex.shtml?applicationName=traffic/road&amp;pageName=ENCLTFREQUERY">
		<actions>
			<action title="搜索" type="submit"/>
		</actions>
	</form>
	
	<form name="ENCLTFRE_SELFQUERY" title="普货经营性运输个体业户查询" pojo="ENCLTFRE" method="get" action="/cms/sitemanage/applicationIndex.shtml?applicationName=traffic/road&amp;pageName=ENCLTFRE_SELFQUERY">
		<actions>
			<action title="搜索" type="submit"/>
		</actions>
	</form>
	
	<form name="ENCLTDAGFREQUERY" title="危货企业查询" pojo="ENCLTDAGFRE" method="get" action="/cms/sitemanage/applicationIndex.shtml?applicationName=traffic/road&amp;pageName=ENCLTDAGFREQUERY">
		<actions>
			<action title="搜索" type="submit"/>
		</actions>
	</form>
	
	<form name="ENTVECFREIGHTQUERY" title="普通货运车辆查询" pojo="ENTVECFREIGHT" method="get" action="/cms/sitemanage/applicationIndex.shtml?applicationName=traffic/road&amp;pageName=ENTVECFREIGHTQUERY">
		<actions>
			<action title="搜索" type="submit"/>
		</actions>
	</form>
	
	<form name="ENTVECDANFREIGHTQUERY" title="危货车辆查询" pojo="ENTVECDANFREIGHT" method="get" action="/cms/sitemanage/applicationIndex.shtml?applicationName=traffic/road&amp;pageName=ENTVECDANFREIGHTQUERY">
		<actions>
			<action title="搜索" type="submit"/>
		</actions>
	</form>
	
	<form name="CMPSNQUERY" title="从业人员查询" pojo="CMPSN" method="get" action="/cms/sitemanage/applicationIndex.shtml?applicationName=traffic/road&amp;pageName=CMPSNQUERY">
		<actions>
			<action title="搜索" type="submit"/>
		</actions>
	</form>
	
	<form name="TECHNICINFOQUERY" title="营运车辆技术档案查询" pojo="TECHNICINFO" method="get" action="/cms/sitemanage/applicationIndex.shtml?applicationName=traffic/road&amp;pageName=TECHNICINFOQUERY">
		<actions>
			<action title="搜索" type="submit"/>
		</actions>
	</form>
	
	<form name="VECEXAQUERY" title="营运车辆年度审验查询" pojo="VECEXA" method="get" action="/cms/sitemanage/applicationIndex.shtml?applicationName=traffic/road&amp;pageName=VECEXAQUERY">
		<actions>
			<action title="搜索" type="submit"/>
		</actions>
	</form>
</forms>